README.md
setup.py
fbgrouter/__init__.py
fbgrouter.egg-info/PKG-INFO
fbgrouter.egg-info/SOURCES.txt
fbgrouter.egg-info/dependency_links.txt
fbgrouter.egg-info/top_level.txt
fbgrouter/classes/__init__.py
fbgrouter/classes/request_handler.py
fbgrouter/classes/router.py