Metadata-Version: 2.1
Name: fbgrouter
Version: 0.1
Summary: fbgrouter - paquete de creación de rutas
Home-page: https://github.com/usuariomen/fbgrouter
Author: Tu Nombre
Author-email: tu.email@example.com
Classifier: Programming Language :: Python :: 3
Classifier: License :: OSI Approved :: MIT License
Classifier: Operating System :: OS Independent
